ba_cuda/__init__.py
ba_cuda/loss.py
ba_cuda/optimizer.py
ba_cuda/projection.py
ba_cuda/se3.py
ba_cuda-0.1.0.dist-info/licenses/LICENSE
ba_cuda-0.1.0.dist-info/METADATA
ba_cuda-0.1.0.dist-info/WHEEL
ba_cuda-0.1.0.dist-info/top_level.txt
ba_cuda-0.1.0.dist-info/RECORD
