Metadata-Version: 2.4
Name: ba-cuda
Version: 0.1.0
Summary: GPU-accelerated Bundle Adjustment using PyTorch with Analytical Jacobians
Author-email: Hunmin Kim <hunminkim98@example.com>
License: MIT
Project-URL: Homepage, https://github.com/hunminkim98/BA_on_CUDA_130_Win
Project-URL: Repository, https://github.com/hunminkim98/BA_on_CUDA_130_Win.git
Keywords: bundle-adjustment,camera-calibration,pytorch,cuda,computer-vision,sfm
Classifier: Development Status :: 4 - Beta
Classifier: Intended Audience :: Developers
Classifier: Intended Audience :: Science/Research
Classifier: License :: OSI Approved :: MIT License
Classifier: Programming Language :: Python :: 3
Classifier: Programming Language :: Python :: 3.10
Classifier: Programming Language :: Python :: 3.11
Classifier: Programming Language :: Python :: 3.12
Classifier: Topic :: Scientific/Engineering :: Image Processing
Classifier: Topic :: Scientific/Engineering :: Artificial Intelligence
Requires-Python: >=3.10
License-File: LICENSE
Requires-Dist: numpy>=1.20.0
Provides-Extra: dev
Requires-Dist: pytest>=7.0.0; extra == "dev"
Requires-Dist: build; extra == "dev"
Requires-Dist: twine; extra == "dev"
Dynamic: license-file
